cardnacki/__init__.py
cardnacki/card.py
cardnacki/card_comparison.py
cardnacki/constants.py
cardnacki/describe_poker_hand.py
cardnacki/pile.py
cardnacki/piles.py
cardnacki/player.py
cardnacki/poker_hand_lu_job.py
cardnacki-0.3.1.dist-info/METADATA
cardnacki-0.3.1.dist-info/WHEEL
cardnacki-0.3.1.dist-info/top_level.txt
cardnacki-0.3.1.dist-info/RECORD
