Metadata-Version: 2.1
Name: cardnacki
Version: 0.3.1
Summary: A playing cards package
Home-page: https://github.com/bernackimark/cardnacki
Author: Bernacki
Author-email: bernackimark@gmail.com
Requires-Python: >=3.10
Provides-Extra: dev
Requires-Dist: twine >=4.0.2 ; extra == 'dev'
